config_parser/__init__.py
config_parser/action_config_parser.py
config_parser/application_config_model.py
config_parser/application_flows_and_actions.py
config_parser/base_config_model.py
config_parser/chart_config_model.py
config_parser/chat_app_config_model.py
config_parser/chat_app_table_config_model.py
config_parser/chat_context_config_model.py
config_parser/component_config_model.py
config_parser/flow_action_config_model.py
config_parser/flow_config_model.py
config_parser/flow_parameter_config_model.py
config_parser/package_config_model.py
config_parser/parameter_config_model.py
config_parser/training_data_config_model.py
config_parser/component_details_config_models/__init__.py
config_parser/component_details_config_models/component_navigation_config_model.py
config_parser/component_details_config_models/component_navigation_details_model.py
config_parser/component_details_config_models/input_component_config_model.py
config_parser/component_details_config_models/output_component_config_model.py
config_parser/component_details_config_models/single_value_navigation_config_model.py
config_parser/component_details_config_models/table_input_navigation_model.py
config_parser/component_details_config_models/text_box_component_config_model.py
config_parser/config_parser_enums/__init__.py
config_parser/config_parser_enums/available_component_navigation_sources.py
config_parser/config_parser_enums/component_relationship_types.py
config_parser/config_parser_enums/component_sizes.py
config_parser/config_parser_enums/component_types.py
config_parser/config_parser_enums/parameter_names.py
dft/__init__.py
dft/base_execution_handler.py
dft/execution_handler/__init__.py
dft/execution_handler/base_execution_handler.py
dft/models/__init__.py
dft/models/chart_config.py
dft/models/chart_data.py
dft/models/chart_metadata.py
dft/models/chart_options/__init__.py
dft/models/chart_options/chart_options.py
dft/models/chart_options/gauge_single_value_options.py
dft-0.1.57.dist-info/LICENSE
dft-0.1.57.dist-info/METADATA
dft-0.1.57.dist-info/WHEEL
dft-0.1.57.dist-info/top_level.txt
dft-0.1.57.dist-info/RECORD
