Metadata-Version: 2.1
Name: dft
Version: 0.1.57
Summary: DF Package
Home-page: https://github.com/TBD
Author: Data Facade
Author-email: info@data-facade.com
Classifier: Programming Language :: Python :: 3
Classifier: License :: OSI Approved :: MIT License
Classifier: Operating System :: OS Independent
Requires-Python: >=3.6
License-File: LICENSE
